adf_builder/__init__.py
adf_builder/doc.py
adf_builder/nodes/__init__.py
adf_builder/nodes/base.py
adf_builder/nodes/marks.py
adf_builder/nodes/inline/__init__.py
adf_builder/nodes/inline/text.py
adf_builder/nodes/top/__init__.py
adf_builder/nodes/top/backup_list.py
adf_builder/nodes/top/code.py
adf_builder/nodes/top/divider.py
adf_builder/nodes/top/heading.py
adf_builder/nodes/top/list.py
adf_builder/nodes/top/panel.py
adf_builder/nodes/top/paragraph.py
adf_builder/nodes/top/quote.py
adf_builder-0.0.1.dist-info/licenses/LICENSE
adf_builder-0.0.1.dist-info/METADATA
adf_builder-0.0.1.dist-info/WHEEL
adf_builder-0.0.1.dist-info/top_level.txt
adf_builder-0.0.1.dist-info/RECORD
