Metadata-Version: 2.4
Name: adf_builder
Version: 0.0.1
Summary: Python builder for the Atlassian Document Format (ADF)
Author-email: Dimitar Ivanov <dimitarxivanov@gmail.com>
License-Expression: MIT
Project-URL: Homepage, https://github.com/dimitarOnGithub/adf_builder
Keywords: adf,builder,atlassian,document,format
Classifier: Development Status :: 1 - Planning
Classifier: Intended Audience :: Developers
Classifier: Operating System :: OS Independent
Classifier: Programming Language :: Python
Classifier: Programming Language :: Python :: 3
Classifier: Programming Language :: Python :: 3 :: Only
Classifier: Programming Language :: Python :: 3.10
Classifier: Programming Language :: Python :: 3.11
Classifier: Programming Language :: Python :: 3.12
Classifier: Programming Language :: Python :: 3.13
Classifier: Programming Language :: Python :: 3.14
Classifier: Topic :: Software Development
Classifier: Topic :: Software Development :: Libraries :: Python Modules
Classifier: Topic :: Utilities
Requires-Python: >=3.10
License-File: LICENSE
Dynamic: license-file
